ellm/__init__.py
ellm/extract/__init__.py
ellm/extract/extract.py
ellm-0.1.0.dist-info/METADATA
ellm-0.1.0.dist-info/WHEEL
ellm-0.1.0.dist-info/RECORD
