Metadata-Version: 2.1
Name: ellm
Version: 0.1.0
Summary: 
Author: weixx
Author-email: weixx@yingmi.cn
Requires-Python: >=3.7,<4.0
Classifier: Programming Language :: Python :: 3
Classifier: Programming Language :: Python :: 3.7
Classifier: Programming Language :: Python :: 3.8
Classifier: Programming Language :: Python :: 3.9
Classifier: Programming Language :: Python :: 3.10
Classifier: Programming Language :: Python :: 3.11
Requires-Dist: jsonpath (==0.82)
Requires-Dist: lxml (==4.9.2)
